MANIFEST.in
README.md
setup.py
Lagring.egg-info/PKG-INFO
Lagring.egg-info/SOURCES.txt
Lagring.egg-info/dependency_links.txt
Lagring.egg-info/requires.txt
Lagring.egg-info/top_level.txt
lagring/__init__.py
lagring/asset.py
lagring/classproperty.py
lagring/core.py
lagring/entity.py
lagring/exception.py
lagring/flask_lagring.py
lagring/logger.py
lagring/assets/__init__.py
lagring/assets/directory.py
lagring/assets/image.py
test/test.py