Metadata-Version: 1.0
Name: Lagring
Version: 0.2.7.1
Summary: Asset storage for Flask
Home-page: https://github.com/neoden/lagring
Author: Lenar Imamutdinov
Author-email: lenar.imamutdinov@gmail.com
License: MIT
Platform: UNKNOWN
